dummy_pkg/_init_.py
rocm_sdk_libraries_gfx110x_dgpu-0.0.2.dist-info/METADATA
rocm_sdk_libraries_gfx110x_dgpu-0.0.2.dist-info/WHEEL
rocm_sdk_libraries_gfx110x_dgpu-0.0.2.dist-info/top_level.txt
rocm_sdk_libraries_gfx110x_dgpu-0.0.2.dist-info/RECORD
