Metadata-Version: 2.4
Name: rocm-sdk-libraries-gfx110x-dgpu
Version: 0.0.2
Summary: rocm-sdk-libraries-gfx110x-dgpu PyPI uploads
Author-email: Shiraz <sali@amd.com>
License: MIT
Project-URL: Homepage, https://rocm.nightlies.amd.com/v2/gfx110X-dgpu/
Requires-Python: >=3.8
